{
    "service": {
        "port": 3000,
        "host": "0.0.0.0",
        "options": {
            "logger": true
        }
    },
    "database": {
        "sequelizeOptions": {
            "database": "todoapp",
            "dialect": "postgres",
            "host": "0.0.0.0",
            "username": "dev",
            "password": "verysecretpassword",
            "port": "5432"
        }
    },
    "helmet": {},
    "swagger": {
        "title": "TODO Service",
        "description": "Todo application for demo purpose",
        "enabled": true
    }
}